n8n_api.py
n8npy_client-0.2.0.dist-info/licenses/LICENSE
n8npy_client-0.2.0.dist-info/METADATA
n8npy_client-0.2.0.dist-info/WHEEL
n8npy_client-0.2.0.dist-info/top_level.txt
n8npy_client-0.2.0.dist-info/RECORD
