Metadata-Version: 2.4
Name: n8npy-client
Version: 0.2.0
Summary: Python client for the n8n Public REST API
Author: splifter
License: Sustainable Use License
Project-URL: Homepage, https://github.com/splifter/n8npy
Project-URL: Documentation, https://github.com/splifter/n8npy
Project-URL: Source, https://github.com/splifter/n8npy
Keywords: n8n,api,client,automation
Classifier: Programming Language :: Python :: 3
Classifier: Programming Language :: Python :: 3 :: Only
Classifier: Operating System :: OS Independent
Requires-Python: >=3.10
License-File: LICENSE
Requires-Dist: requests>=2.31.0
Requires-Dist: python-dotenv>=1.0.0
Provides-Extra: dev
Requires-Dist: pytest>=7.4; extra == "dev"
Requires-Dist: responses>=0.25; extra == "dev"
Requires-Dist: pyyaml>=6.0; extra == "dev"
Requires-Dist: jsonref>=1.1.0; extra == "dev"
Requires-Dist: build>=1.0; extra == "dev"
Requires-Dist: twine>=4.0; extra == "dev"
Dynamic: license-file
